fa2_custom_mask/__init__.py
fa2_custom_mask/fa2_bwd.py
fa2_custom_mask/fa2_custom_mask.py
fa2_custom_mask/fa2_fwd.py
fa2_custom_mask/utils.py
flashattention2_custom_mask-0.1.1.dist-info/LICENSE
flashattention2_custom_mask-0.1.1.dist-info/METADATA
flashattention2_custom_mask-0.1.1.dist-info/WHEEL
flashattention2_custom_mask-0.1.1.dist-info/top_level.txt
flashattention2_custom_mask-0.1.1.dist-info/RECORD
