Metadata-Version: 2.1
Name: flashattention2-custom-mask
Version: 0.1.1
Summary: Unofficial FlashAttention2 with Custom Masks
Author-email: Alex Zhang <alzhang@alumni.princeton.edu>
Keywords: flash attention,triton,pytorch
Requires-Python: >=3.8
License-File: LICENSE
Requires-Dist: pytest ~=8.3.1
Requires-Dist: triton ~=3.0.0
Requires-Dist: torch ~=2.2.1
Requires-Dist: numpy ==1.26.4
